{"type":"FeatureCollection","features":[{"type":"Feature","properties":{"POI_ID":1,"poiName":"Puerto Maldonado","infoPOI":"Puerto Maldonado is the capital city of Madre de Dios region, population >80,000"},"geometry":{"type":"Point","coordinates":[-69.19555,-12.59132]}},{"type":"Feature","properties":{"POI_ID":2,"poiName":"Interoceanic Highway","infoPOI":"The Interoceanic Highway was officially opened in 2012. This international, transcontinental highway runs through the Amazon, connecting Peru’s Pacific ports to Brazil’s Atlantic coast."},"geometry":{"type":"Point","coordinates":[-69.923598,-12.91276]}}]}